[
  {
    "Name": "Shana",
    "Surname": "Kline",
    "Gender": "female",
    "KnownAs": "Shana",
    "Introduction": "Aliquip ipsum eu anim nulla nulla. Et exercitation magna magna proident. Dolore officia voluptate elit mollit aliquip aliqua. Exercitation amet dolore non dolor magna voluptate ullamco deserunt mollit duis mollit in.\r\n",
    "DateOfBirth": "1954-12-02",
    "Created": "2019-12-24",
    "LastActive": "2020-06-24",
    "Email": "shanakline@gynk.com",
    "PhoneNumber": "+1 (810) 538-3962",
    "Address": {
      "Street": "Musterstraße",
      "HouseNumber": "12A",
      "Zip": "20095",
      "City": "Hamburg",
      "Country": "Germany"
    },
    "UserPhotos": [
      {
        "Url": "https://randomuser.me/api/portraits/women/93.jpg",
        "IsMain": true
      }
    ]
  },
  {
    "Name": "Anastasia",
    "Surname": "Kidd",
    "Gender": "female",
    "KnownAs": "Anastasia",
    "Introduction": "Velit sint ullamco irure exercitation qui aute dolore excepteur non deserunt. Id aliquip commodo tempor esse reprehenderit aliquip amet eiusmod. Ad ex nisi tempor cupidatat deserunt cillum commodo in.\r\n",
    "DateOfBirth": "1979-02-27",
    "Created": "2020-06-04",
    "LastActive": "2020-06-26",
    "Email": "anastasiakidd@gynk.com",
    "PhoneNumber": "+1 (891) 570-3643",
    "Address": {
      "Street": "Berliner Allee",
      "HouseNumber": "45B",
      "Zip": "10117",
      "City": "Berlin",
      "Country": "Germany"
    },
    "UserPhotos": [
      {
        "Url": "https://randomuser.me/api/portraits/women/44.jpg",
        "IsMain": true
      }
    ]
  },
  {
    "Name": "Janell",
    "Surname": "Hooper",
    "Gender": "female",
    "KnownAs": "Janell",
    "Introduction": "Laboris mollit dolor deserunt exercitation consequat quis mollit aute eu dolor aliqua reprehenderit. Non reprehenderit labore esse mollit. Qui ut magna ad mollit quis culpa eu consequat irure fugiat nostrud. Laboris culpa esse esse consequat do velit quis qui sit aute enim.\r\n",
    "DateOfBirth": "1965-03-21",
    "Created": "2020-04-25",
    "LastActive": "2020-05-16",
    "Email": "janellhooper@gynk.com",
    "PhoneNumber": "+1 (974) 426-3114",
    "Address": {
      "Street": "Berliner Allee",
      "HouseNumber": "45B",
      "Zip": "10117",
      "City": "Berlin",
      "Country": "Germany"
    },
    "UserPhotos": [
      {
        "Url": "https://randomuser.me/api/portraits/women/74.jpg",
        "IsMain": true
      }
    ]
  },
  {
    "Name": "Mari",
    "Surname": "William",
    "Gender": "female",
    "KnownAs": "Mari",
    "Introduction": "Eiusmod veniam tempor ipsum culpa fugiat do veniam cillum aliqua sunt aute reprehenderit laborum. Cillum est enim nisi irure id nulla. Elit cillum do elit nisi amet ex amet. Lorem nisi id nulla Lorem. Ad non pariatur duis culpa culpa do laboris dolor. Minim id quis ea Lorem dolore minim minim est exercitation do id est. Voluptate eiusmod eu adipisicing incididunt sint ad sit Lorem commodo.\r\n",
    "DateOfBirth": "1958-09-23",
    "Created": "2019-03-21",
    "LastActive": "2020-06-24",
    "Email": "mariwilliam@gynk.com",
    "PhoneNumber": "+1 (910) 511-3861",
    "Address": {
      "Street": "Berliner Allee",
      "HouseNumber": "45B",
      "Zip": "10117",
      "City": "Berlin",
      "Country": "Germany"
    },
    "UserPhotos": [
      {
        "Url": "https://randomuser.me/api/portraits/women/34.jpg",
        "IsMain": true
      }
    ]
  },
  {
    "Name": "Elaine",
    "Surname": "Norris",
    "Gender": "female",
    "KnownAs": "Elaine",
    "Introduction": "Adipisicing dolor ea officia laborum deserunt est cupidatat fugiat fugiat laboris. Nisi officia aliqua excepteur dolor id. Do irure ipsum ex commodo. Laboris cillum officia mollit laborum duis non do nulla officia.\r\n",
    "DateOfBirth": "1967-08-18",
    "Created": "2020-02-28",
    "LastActive": "2020-05-19",
    "Email": "elainenorris@gynk.com",
    "PhoneNumber": "+1 (926) 572-3182",
    "Address": {
      "Street": "Berliner Allee",
      "HouseNumber": "45B",
      "Zip": "10117",
      "City": "Berlin",
      "Country": "Germany"
    },
    "UserPhotos": [
      {
        "Url": "https://randomuser.me/api/portraits/women/26.jpg",
        "IsMain": true
      }
    ]
  },
  {
    "Name": "Garner",
    "Surname": "Stark",
    "Gender": "male",
    "KnownAs": "Garner",
    "Introduction": "Amet Lorem aliqua et culpa qui qui ipsum cupidatat minim. Non laborum in amet esse qui ullamco Lorem nisi. Nulla esse cupidatat occaecat eu elit mollit. Aliquip irure mollit tempor irure labore nostrud officia tempor.\r\n",
    "DateOfBirth": "1954-12-01",
    "Created": "2020-03-21",
    "LastActive": "2020-06-25",
    "Email": "garnerstark@gynk.com",
    "PhoneNumber": "+1 (808) 576-2913",
    "Address": {
      "Street": "Berliner Allee",
      "HouseNumber": "45B",
      "Zip": "10117",
      "City": "Berlin",
      "Country": "Germany"
    },
    "UserPhotos": [
      {
        "Url": "https://randomuser.me/api/portraits/men/78.jpg",
        "IsMain": true
      }
    ]
  },
  {
    "Name": "Phillips",
    "Surname": "Phillips",
    "Gender": "male",
    "KnownAs": "Phillips",
    "Introduction": "Duis ipsum occaecat consectetur et sit. Velit elit elit esse aliqua Lorem ullamco enim id esse cupidatat proident sit. Qui consectetur culpa aute proident.\r\n",
    "DateOfBirth": "1952-08-15",
    "Created": "2020-04-01",
    "LastActive": "2020-05-17",
    "Email": "phillipsphillips@gynk.com",
    "PhoneNumber": "+1 (916) 517-2671",
    "Address": {
      "Street": "Berliner Allee",
      "HouseNumber": "45B",
      "Zip": "10117",
      "City": "Berlin",
      "Country": "Germany"
    },
    "UserPhotos": [
      {
        "Url": "https://randomuser.me/api/portraits/men/79.jpg",
        "IsMain": true
      }
    ]
  },
  {
    "Name": "Sutton",
    "Surname": "Kelly",
    "Gender": "male",
    "KnownAs": "Sutton",
    "Introduction": "In commodo sint nulla irure minim sint nisi deserunt adipisicing veniam id. Non sit sint tempor ut occaecat exercitation ex exercitation commodo eiusmod deserunt labore. Magna in velit magna incididunt velit voluptate anim pariatur sunt. Velit magna aliquip ea magna ea eiusmod ad sint duis officia ullamco excepteur enim enim. Do consequat excepteur consequat excepteur. Excepteur proident non veniam Lorem tempor ad fugiat veniam ullamco consequat cillum.\r\n",
    "DateOfBirth": "1989-12-20",
    "Created": "2020-04-19",
    "LastActive": "2020-05-29",
    "Email": "suttonkelly@gynk.com",
    "PhoneNumber": "+1 (983) 452-2372",
    "Address": {
      "Street": "Berliner Allee",
      "HouseNumber": "45B",
      "Zip": "10117",
      "City": "Berlin",
      "Country": "Germany"
    },
    "UserPhotos": [
      {
        "Url": "https://randomuser.me/api/portraits/men/18.jpg",
        "IsMain": true
      }
    ]
  },
  {
    "Name": "Patton",
    "Surname": "Ware",
    "Gender": "male",
    "KnownAs": "Patton",
    "Introduction": "Ea eiusmod irure aliquip dolor ut dolore nulla ad proident sint. Irure officia adipisicing ullamco cillum nulla eu occaecat laborum fugiat esse exercitation. Ut tempor nisi ut ullamco dolore anim. Sit culpa consequat ad voluptate et elit ullamco ea veniam nulla irure incididunt commodo deserunt. Ea consectetur quis fugiat reprehenderit dolore esse incididunt enim sunt elit. Ex laboris fugiat laboris nostrud deserunt esse irure ullamco officia. Esse mollit est sunt consequat magna labore cillum sint.\r\n",
    "DateOfBirth": "1968-07-01",
    "Created": "2020-06-06",
    "LastActive": "2020-06-10",
    "Email": "pattonware@gynk.com",
    "PhoneNumber": "+1 (882) 442-2976",
    "Address": {
      "Street": "Berliner Allee",
      "HouseNumber": "45B",
      "Zip": "10117",
      "City": "Berlin",
      "Country": "Germany"
    },
    "UserPhotos": [
      {
        "Url": "https://randomuser.me/api/portraits/men/7.jpg",
        "IsMain": true
      }
    ]
  },
  {
    "Name": "Sanchez",
    "Surname": "Blake",
    "Gender": "male",
    "KnownAs": "Sanchez",
    "Introduction": "Ex consequat eu exercitation consectetur. Adipisicing voluptate aute ex in sunt laboris. Aliqua deserunt incididunt veniam Lorem ipsum deserunt incididunt tempor.\r\n",
    "DateOfBirth": "1982-02-03",
    "Created": "2019-07-27",
    "LastActive": "2020-06-20",
    "Email": "sanchezblake@gynk.com",
    "PhoneNumber": "+1 (932) 507-2858",
    "Address": {
      "Street": "Berliner Allee",
      "HouseNumber": "45B",
      "Zip": "10117",
      "City": "Berlin",
      "Country": "Germany"
    },
    "UserPhotos": [
      {
        "Url": "https://randomuser.me/api/portraits/men/99.jpg",
        "IsMain": true
      }
    ]
  }
]